sureal/__init__.py
sureal/__main__.py
sureal/cmd_deprecated.py
sureal/config.py
sureal/dataset_reader.py
sureal/experimental.py
sureal/pc_subjective_model.py
sureal/perf_metric.py
sureal/routine.py
sureal/subjective_model.py
sureal/core/__init__.py
sureal/core/mixin.py
sureal/tools/__init__.py
sureal/tools/decorator.py
sureal/tools/inverse.py
sureal/tools/misc.py
sureal/tools/stats.py
sureal-0.9.0.dist-info/LICENSE
sureal-0.9.0.dist-info/METADATA
sureal-0.9.0.dist-info/NOTICE.md
sureal-0.9.0.dist-info/WHEEL
sureal-0.9.0.dist-info/entry_points.txt
sureal-0.9.0.dist-info/top_level.txt
sureal-0.9.0.dist-info/RECORD
