Metadata-Version: 2.1
Name: sureal
Version: 0.9.0
Summary: Subjective Recovery Analysis
Home-page: https://github.com/Netflix/sureal
Author: Zhi Li
Author-email: zli@netflix.com
License: Apache 2.0
Classifier: License :: OSI Approved :: Apache Software License
Classifier: Operating System :: MacOS
Classifier: Operating System :: Unix
Classifier: Programming Language :: Python :: 2
Classifier: Programming Language :: Python :: 2.7
Classifier: Programming Language :: Python :: 3
License-File: LICENSE
License-File: NOTICE.md
Requires-Dist: numpy (>=1.12.0)
Requires-Dist: scipy (>=0.17.1)
Requires-Dist: matplotlib (>=2.0.0)
Requires-Dist: pandas (>=0.19.2)
Requires-Dist: setupmeta
